odoo/addons/sale_force_whole_invoiceability/README.rst
odoo/addons/sale_force_whole_invoiceability/__init__.py
odoo/addons/sale_force_whole_invoiceability/__manifest__.py
odoo/addons/sale_force_whole_invoiceability/i18n/es.po
odoo/addons/sale_force_whole_invoiceability/i18n/it.po
odoo/addons/sale_force_whole_invoiceability/i18n/sale_force_whole_invoiceability.pot
odoo/addons/sale_force_whole_invoiceability/models/__init__.py
odoo/addons/sale_force_whole_invoiceability/models/sale_order.py
odoo/addons/sale_force_whole_invoiceability/readme/CONTRIBUTORS.md
odoo/addons/sale_force_whole_invoiceability/readme/DESCRIPTION.md
odoo/addons/sale_force_whole_invoiceability/readme/ROADMAP.md
odoo/addons/sale_force_whole_invoiceability/readme/USAGE.md
odoo/addons/sale_force_whole_invoiceability/static/description/icon.png
odoo/addons/sale_force_whole_invoiceability/static/description/index.html
odoo/addons/sale_force_whole_invoiceability/tests/__init__.py
odoo/addons/sale_force_whole_invoiceability/tests/test_sale_force_whole.py
odoo/addons/sale_force_whole_invoiceability/views/sale_order_views.xml
odoo_addon_sale_force_whole_invoiceability-17.0.1.0.0.5.dist-info/METADATA
odoo_addon_sale_force_whole_invoiceability-17.0.1.0.0.5.dist-info/WHEEL
odoo_addon_sale_force_whole_invoiceability-17.0.1.0.0.5.dist-info/top_level.txt
odoo_addon_sale_force_whole_invoiceability-17.0.1.0.0.5.dist-info/RECORD
